micropython.py
setup.py
pycopy_cpython_micropython.egg-info/PKG-INFO
pycopy_cpython_micropython.egg-info/SOURCES.txt
pycopy_cpython_micropython.egg-info/dependency_links.txt
pycopy_cpython_micropython.egg-info/requires.txt
pycopy_cpython_micropython.egg-info/top_level.txt